{"Caption":"Figure 12. (a) The original images; (b) the clustering results using CLEAN","ImageText":[{"Text":"Figure.","TextBB":[241.5,303.962,280.037,315.212],"Rotation":0},{"Text":"10.","TextBB":[283.204,303.962,298.745,315.212],"Rotation":0},{"Text":"The","TextBB":[301.911,303.962,322.749,315.212],"Rotation":0},{"Text":"clustering","TextBB":[325.832,303.962,378.607,315.212],"Rotation":0},{"Text":"results","TextBB":[381.691,303.962,417.104,315.212],"Rotation":0},{"Text":"of","TextBB":[420.25,303.962,430.661,315.212],"Rotation":0},{"Text":"(a)","TextBB":[433.826,303.962,448.398,315.212],"Rotation":0},{"Text":"CHAMELEON;","TextBB":[451.563,303.962,539.05,315.212],"Rotation":0},{"Text":"(b)","TextBB":[542.215,303.962,557.487,315.212],"Rotation":0},{"Text":"CLEAN;","TextBB":[560.652,303.962,608.558,315.212],"Rotation":0}],"Mention":["This section will evaluate the automatic version of CLEAN, i.e., \nusing the learning approach to decide the boundary layer \nautomatically instead of user intervention. Figure 12. (a) shows \ntwo security images used by Yahoo to prevent automatic form \nfilling in application of email address. Yahoo requires the user to \nrecognize the letters by visual inspection and fill them into the \napplication form so that programs for auto-filling fail. This means \nsuch images may be difficult to be recognized by computer \nprograms. We collect a series of such images from Yahoo website \nand all of them have similar properties on size and noise ratio, so \n"," at 20 due to the images have similar sizes. Figure 12 (b) \n"],"Page":7,"Number":12,"Type":"Figure","CaptionBB":[225,515,623,528],"Height":1100,"Width":850,"DPI":100,"ImageBB":[109,99,740,515]}