{"Caption":"Figure 5: Boolean Network Expression","ImageText":[{"Text":"`","TextBB":[120.337,774.383,125.728,787.733],"Rotation":0},{"Text":"´","TextBB":[335.3,774.383,340.691,787.733],"Rotation":0},{"Text":"D","TextBB":[125.737,775.934,135.39,784.07],"Rotation":0},{"Text":"|","TextBB":[142.25,775.535,145.516,786.605],"Rotation":0},{"Text":"(A","TextBB":[152.05,775.535,165.436,786.605],"Rotation":0},{"Text":"B","TextBB":[168.7,775.934,177.567,784.07],"Rotation":0},{"Text":"C","TextBB":[181.371,775.934,189.751,784.07],"Rotation":0},{"Text":"E","TextBB":[193.806,775.934,202.429,784.07],"Rotation":0},{"Text":"F","TextBB":[206.322,775.934,213.761,784.07],"Rotation":0},{"Text":"G","TextBB":[218.663,775.934,227.828,784.07],"Rotation":0},{"Text":"H","TextBB":[231.1,775.934,240.764,784.07],"Rotation":0},{"Text":"J","TextBB":[244.876,775.934,251.297,784.07],"Rotation":0},{"Text":"K","TextBB":[255.609,775.934,265.527,784.07],"Rotation":0},{"Text":"L","TextBB":[269.575,775.934,277.578,784.07],"Rotation":0},{"Text":"M","TextBB":[280.837,775.934,292.128,784.07],"Rotation":0},{"Text":"X","TextBB":[296.583,775.934,306.258,784.07],"Rotation":0},{"Text":"X","TextBB":[315.287,775.934,324.962,784.07],"Rotation":0},{"Text":")","TextBB":[330.725,775.535,335.296,786.605],"Rotation":0},{"Text":"and","TextBB":[344.613,775.912,365.088,784.081],"Rotation":0},{"Text":"1","TextBB":[306.262,779.148,311.335,787.451],"Rotation":0},{"Text":"2","TextBB":[324.962,779.148,330.035,787.451],"Rotation":0},{"Text":"´","TextBB":[234.949,788.307,240.34,801.657],"Rotation":0},{"Text":"`","TextBB":[120.338,788.308,125.728,801.657],"Rotation":0},{"Text":"`","TextBB":[120.337,802.245,125.728,815.595],"Rotation":0},{"Text":"L","TextBB":[125.737,789.859,133.741,797.995],"Rotation":0},{"Text":"|","TextBB":[140.262,789.46,143.528,800.53],"Rotation":0},{"Text":"(C","TextBB":[150.062,789.46,163.017,800.53],"Rotation":0},{"Text":"F","TextBB":[167.075,789.859,174.514,797.995],"Rotation":0},{"Text":"H","TextBB":[179.408,789.859,189.072,797.995],"Rotation":0},{"Text":"J","TextBB":[193.2,789.859,199.62,797.995],"Rotation":0},{"Text":"K","TextBB":[203.924,789.859,213.842,797.995],"Rotation":0},{"Text":"M","TextBB":[217.899,789.859,229.19,797.995],"Rotation":0},{"Text":")","TextBB":[230.374,789.46,234.945,800.53],"Rotation":0},{"Text":"and","TextBB":[244.262,789.837,264.737,798.006],"Rotation":0},{"Text":"´","TextBB":[321.013,802.245,326.404,815.595],"Rotation":0},{"Text":"(A","TextBB":[125.737,803.385,139.124,814.455],"Rotation":0},{"Text":"B","TextBB":[142.389,803.784,151.256,811.92],"Rotation":0},{"Text":"E","TextBB":[155.075,803.784,163.698,811.92],"Rotation":0},{"Text":"G)","TextBB":[167.579,803.784,181.309,811.92],"Rotation":0},{"Text":"|","TextBB":[187.85,803.385,191.116,814.455],"Rotation":0},{"Text":"C","TextBB":[197.65,803.784,206.03,811.92],"Rotation":0},{"Text":"|","TextBB":[213.35,803.385,216.615,814.455],"Rotation":0},{"Text":"D","TextBB":[223.15,803.784,232.802,811.92],"Rotation":0},{"Text":"|","TextBB":[239.662,803.385,242.928,814.455],"Rotation":0},{"Text":"L","TextBB":[249.462,803.784,257.465,811.92],"Rotation":0},{"Text":"|","TextBB":[264,803.385,267.265,814.455],"Rotation":0},{"Text":"X","TextBB":[273.8,803.784,283.475,811.92],"Rotation":0},{"Text":"|","TextBB":[295.775,803.385,299.04,814.455],"Rotation":0},{"Text":"X","TextBB":[305.575,803.784,315.25,811.92],"Rotation":0},{"Text":"and","TextBB":[330.325,803.762,350.801,811.931],"Rotation":0},{"Text":"1","TextBB":[283.475,806.998,288.548,815.301],"Rotation":0},{"Text":"2","TextBB":[315.251,806.998,320.323,815.301],"Rotation":0},{"Text":"´","TextBB":[286.3,816.17,291.691,829.52],"Rotation":0},{"Text":"`","TextBB":[120.338,816.17,125.729,829.52],"Rotation":0},{"Text":"´","TextBB":[354.45,830.095,359.841,843.445],"Rotation":0},{"Text":"`","TextBB":[120.338,830.095,125.728,843.445],"Rotation":0},{"Text":"(A","TextBB":[125.738,817.323,139.124,828.393],"Rotation":0},{"Text":"B","TextBB":[142.389,817.721,151.256,825.857],"Rotation":0},{"Text":"E","TextBB":[155.075,817.721,163.698,825.857],"Rotation":0},{"Text":"G)","TextBB":[167.579,817.721,181.309,825.857],"Rotation":0},{"Text":"|","TextBB":[187.85,817.323,191.116,828.392],"Rotation":0},{"Text":"(C","TextBB":[197.65,817.323,210.605,828.392],"Rotation":0},{"Text":"L)","TextBB":[214.66,817.721,227.235,825.857],"Rotation":0},{"Text":"|","TextBB":[233.763,817.323,237.029,828.392],"Rotation":0},{"Text":"(F","TextBB":[243.563,817.323,255.577,828.392],"Rotation":0},{"Text":"H","TextBB":[260.489,817.721,270.153,825.857],"Rotation":0},{"Text":"J)","TextBB":[274.265,817.721,286.298,825.857],"Rotation":0},{"Text":"and","TextBB":[295.613,817.699,316.088,825.869],"Rotation":0},{"Text":"(F","TextBB":[125.737,831.248,137.751,842.318],"Rotation":0},{"Text":"H","TextBB":[142.645,831.646,152.309,839.782],"Rotation":0},{"Text":"J)","TextBB":[156.437,831.646,168.472,839.782],"Rotation":0},{"Text":"|","TextBB":[175,831.248,178.266,842.317],"Rotation":0},{"Text":"(A","TextBB":[184.813,831.248,198.199,842.317],"Rotation":0},{"Text":"B","TextBB":[201.462,831.646,210.329,839.782],"Rotation":0},{"Text":"C","TextBB":[214.137,831.646,222.517,839.782],"Rotation":0},{"Text":"E","TextBB":[226.572,831.646,235.195,839.782],"Rotation":0},{"Text":"G)","TextBB":[239.087,831.646,252.822,839.782],"Rotation":0},{"Text":"|","TextBB":[259.35,831.248,262.616,842.317],"Rotation":0},{"Text":"(A","TextBB":[269.15,831.248,282.536,842.317],"Rotation":0},{"Text":"B","TextBB":[285.814,831.646,294.681,839.782],"Rotation":0},{"Text":"E","TextBB":[298.485,831.646,307.108,839.782],"Rotation":0},{"Text":"G","TextBB":[311.001,831.646,320.167,839.782],"Rotation":0},{"Text":"K","TextBB":[323.427,831.646,333.346,839.782],"Rotation":0},{"Text":"M","TextBB":[337.401,831.646,348.692,839.782],"Rotation":0},{"Text":")","TextBB":[349.876,831.248,354.448,842.317],"Rotation":0}],"Mention":["To mine the minimal and closed and-clauses, we build\nuponBLOSOM-MO andBLOSOM-CO, respectively. Note\nthat by DeMorgan\u2019s law, to mine the minimal and-clauses,\nwe can mine the minimal or-clauses over the complemented\ntidsets. For example in our example dataset in Fig. 1, with\nT = 12345, we have t(AB) = t(A)∩t(B) = 134∩23 = 3. We\n","work. We generated the truth table corresponding to the\n7 input genes but BLOSOM was provided the values for\nall genes, without explicit instruction about which are in-\nputs and which are outputs. This yields a dataset with\n128 rows and 16 items (genes). We then ran BLOSOM\nto discover the boolean expression corresponding to this\ngene network; we used min sup = 100%, since we want\nto find expressions that are true for the entire set of assign-\nments. BLOSOM output 65 expressions in 0.36s, which\nhold true for the entire dataset. After simplification these\ncan be reduced to the equivalent expression, as shown in\nFig. 5. We verified that indeed this expression is true for\nall the rows in the dataset! It also allows us to recon-\nstruct the boolean gene network shown in Fig. 4. For ex-\nample, the first component of the expression in the first row\n"],"Page":6,"Number":5,"Type":"Figure","CaptionBB":[113,850,366,864],"Height":1100,"Width":850,"DPI":100,"ImageBB":[102,768,383,850]}